kion_vectorstore/.env
kion_vectorstore/README.md
kion_vectorstore/__init__.py
kion_vectorstore/app.py
kion_vectorstore/base.py
kion_vectorstore/cli_init_env.py
kion_vectorstore/config.py
kion_vectorstore/document.py
kion_vectorstore/dotenv_finder.py
kion_vectorstore/embeddings.py
kion_vectorstore/file_loader.py
kion_vectorstore/llm.py
kion_vectorstore/manage_vectorstore.py
kion_vectorstore/pdf_file_loader.py
kion_vectorstore/pdf_image_loader.py
kion_vectorstore/pgvector_plugin.py
kion_vectorstore/recursive_text_splitter.py
kion_vectorstore/setup_config.py
kion_vectorstore/text_file_loader.py
kion_vectorstore/static/chat.html
kion_vectorstore/static/file_loader_gui.html
kion_vectorstore/static/file_remover_gui.html
kion_vectorstore-0.2.3.dist-info/licenses/LICENSE
kion_vectorstore-0.2.3.dist-info/METADATA
kion_vectorstore-0.2.3.dist-info/WHEEL
kion_vectorstore-0.2.3.dist-info/entry_points.txt
kion_vectorstore-0.2.3.dist-info/top_level.txt
kion_vectorstore-0.2.3.dist-info/RECORD
