Metadata-Version: 2.4
Name: kion-vectorstore
Version: 0.2.3
Summary: Kion Consulting: Postgres (pgvector) vector database file management library and web GUI.
Home-page: https://github.com/Thoriso-Molefe/kion-vectorstore
Author: Kion Consulting
Author-email: Kion Consulting <thoriso@kion.co.za>
License: MIT License
Project-URL: Homepage, https://github.com/Thoriso-Molefe/kion_vectorstore
Project-URL: Bug Tracker, https://github.com/Thoriso-Molefe/kion_vectorstore/issues
Project-URL: Documentation, https://github.com/Thoriso-Molefe/kion_vectorstore
Keywords: pgvector,postgresql,rag,vectorstore,flask,openai
Classifier: Development Status :: 3 - Alpha
Classifier: Intended Audience :: Developers
Classifier: License :: OSI Approved :: MIT License
Classifier: Programming Language :: Python :: 3
Classifier: Programming Language :: Python :: 3.8
Classifier: Programming Language :: Python :: 3.9
Classifier: Programming Language :: Python :: 3.10
Classifier: Programming Language :: Python :: 3.11
Classifier: Operating System :: OS Independent
Classifier: Topic :: Software Development :: Libraries
Classifier: Framework :: Flask
Requires-Python: >=3.8
License-File: LICENSE
Requires-Dist: python-dotenv
Requires-Dist: flask
Requires-Dist: flask-cors
Requires-Dist: psycopg2-binary
Requires-Dist: PyPDF2
Requires-Dist: pgvector
Requires-Dist: openai
Requires-Dist: sqlalchemy
Requires-Dist: tiktoken
Requires-Dist: sentence_transformers
Requires-Dist: open-clip-torch
Requires-Dist: pillow
Requires-Dist: pymupdf
Requires-Dist: PyMuPDF
Requires-Dist: pytesseract
Requires-Dist: transformers
Requires-Dist: sentence-transformers
Requires-Dist: torch
Requires-Dist: torchvision
Dynamic: author
Dynamic: home-page
Dynamic: license-file
Dynamic: requires-python
